{
  "movies": [
    {
      "id": "inception",
      "title": "Inception",
      "type": "movie",
      "poster": "assets/inception.jpg",
      "trailer_url": "https://www.youtube.com/embed/YoHD9XEInc0",
      "download_url": "https://gofile.io/d/A3TZ3k"
    },
    {
      "id": "darkknight",
      "title": "The Dark Knight",
      "type": "movie",
      "poster": "assets/darkknight.jpg",
      "trailer_url": "https://www.youtube.com/embed/EXeTwQWrcwY?si=JpQpKSKbi38KR3to",
      "download_url": "https://gofile.io/d/ba0kcv"
    },
    {
      "id": "thunderbolts",
      "title": "Thunderbolts",
      "type": "movie",
      "poster": "assets/thunderbolts.jpg",
      "trailer_url": "https://www.youtube.com/embed/v-94Snw-H4o?si=hxuXTUhea9xJ73vb",
      "download_url": "https://gofile.io/d/xWU6pA"
    },
    {
      "id": "breakingbad",
      "title": "Breaking Bad S01 E01",
      "type": "series",
      "poster": "assets/breakingbad.jpg",
      "trailer_url": "https://www.youtube.com/embed/HhesaQXLuRY",
      "download_url": "https://gofile.io/d/28Aa0u"
    },
    {
      "id": "strangerthings",
      "title": "Stranger Things S01 E01",
      "type": "series",
      "poster": "assets/strangerthing.jpg",
      "trailer_url": "https://www.youtube.com/embed/b9EkMc79ZSU",
      "download_url": "https://gofile.io/d/yQMtlZ"
    },
    {
      "id": "gameofthrones",
      "title": "Game of Thrones",
      "type": "series",
      "poster": "assets/gameofthrone.jpg",
      "trailer_url": "https://www.youtube.com/embed/bjqEWgDVPe0?si=PdgInJ5itIHT_DdZ",
      "download_url": "https://gofile.io/d/placeholder1"
    },
    {
      "id": "thewitcher",
      "title": "The Witcher S01 E01",
      "type": "series",
      "poster": "assets/witcher.jpg",
      "trailer_url": "https://www.youtube.com/embed/ndl1W4ltcmg",
      "download_url": "https://gofile.io/d/osHGsx"
    },
        {
      "id": "Dark",
      "title": "The Dark S01 Complete",
      "type": "series",
      "poster": "assets/dark.jpg",
      "trailer_url": "https://www.youtube.com/embed/ESEUoa-mz2c?si=2jxJ_R1xkeGeByg2",
      "download_url": "https://gofile.io/d/oOm3iZ"
    },
    {
      "id": "Caption america brave world",
      "title": "Captain America: Brave New World",
      "type": "movie",
      "poster": "assets/braveworld.jpg",
      "trailer_url": "https://www.youtube.com/embed/1pHDWnXmK7Y?si=JqOyF0pIc215pGo-",
      "download_url": "https://gofile.io/d/Y4XIA0"
    },
 
    {
      "id": "Peaky blinder1",
      "title": "Peaky Blinders Hindi+English Complete S01 ",
      "type": "series",
      "poster": "assets/peaky.jpg",
      "trailer_url": "https://www.youtube.com/embed/X3PGOaEfCmQ?si=INJvm6Itx8YV-yYg",
      "download_url": "https://gofile.io/d/TLeH77"
    },
    {
      "id": "Kesari_Chapter_2",
      "title": "Kesari_Chapter_2 ",
      "type": "movie",
      "poster": "assets/kesari.jpg",
      "trailer_url": "https://jolls346dae.com/play/tt3562110",
      "download_url": "https://gofile.io/d/pFD1ly"
    },
    {
      "id": "Looper",
      "title": "Looper 2012 ",
      "type": "movie",
      "poster": "assets/looper.jpg",
      "trailer_url": "https://www.youtube.com/embed/8Ltpa4QmnuU?si=S4OMlIYshMjU4IaN",
      "download_url": "https://gofile.io/d/jZ0JFM"
    },
    {
      "id": "Abraham_Lincoln_Vampire_Hunter_2012",
      "title": "Abraham_Lincoln_Vampire_Hunter_2012",
      "type": "movie",
      "poster": "assets/abhram.jpg",
      "trailer_url": "https://www.youtube.com/embed/VPTdlrN4AFI?si=HtlcipNxglgHeDTZ",
      "download_url": "https://gofile.io/d/Qz6DLY"
    },
    {
      "id": "Need for Speed",
      "title": "Need For Speed ",
      "type": "movie",
      "poster": "assets/nfs.jpg",
      "trailer_url": "https://www.youtube.com/embed/u3wtVI-aJuw?si=zc_ih9K3wU-BF2b0",
      "download_url": "https://gofile.io/d/h4R8Cs"
    }
    
 
  
  ]
}
